half_utils/__init__.py
half_utils/file_utils.py
half_utils/json_utils.py
half_utils/logger_helper.py
half_utils/module_utils.py
half_utils/version.py
half_utils-1.0.1.dist-info/LICENSE
half_utils-1.0.1.dist-info/METADATA
half_utils-1.0.1.dist-info/WHEEL
half_utils-1.0.1.dist-info/top_level.txt
half_utils-1.0.1.dist-info/RECORD
