Metadata-Version: 2.1
Name: half_utils
Version: 1.0.1
Summary: Useful tool class
Author-email: Half_nothing <Half_nothing@163.com>
License: GPL-3.0-only
Project-URL: Homepage, https://github.com/half-nothing/python-utils
Project-URL: Issues, https://github.com/half-nothing/python-utils/issues
Classifier: Development Status :: 3 - Alpha
Classifier: Programming Language :: Python :: 3
Classifier: Operating System :: OS Independent
Requires-Python: >=3.12
License-File: LICENSE
Requires-Dist: json5>=0.10.0
Requires-Dist: loguru>=0.7.3
